cameron/__init__.py
cameron/control.py
cameron/data_types.py
cameron/matplotlib.py
Camerons_Python-0.0.2.dist-info/LICENSE.md
Camerons_Python-0.0.2.dist-info/METADATA
Camerons_Python-0.0.2.dist-info/WHEEL
Camerons_Python-0.0.2.dist-info/top_level.txt
Camerons_Python-0.0.2.dist-info/RECORD
